rivr_jinja/__init__.py
rivr_jinja/middleware.py
rivr_jinja/response.py
rivr_jinja/view.py
tests/__init__.py
tests/test_middleware.py
tests/test_response.py
rivr_jinja-0.4.1.dist-info/LICENSE
rivr_jinja-0.4.1.dist-info/METADATA
rivr_jinja-0.4.1.dist-info/WHEEL
rivr_jinja-0.4.1.dist-info/top_level.txt
rivr_jinja-0.4.1.dist-info/RECORD
